parendum_astra_api/__init__.py
parendum_astra_api-0.1.3.dist-info/LICENSE
parendum_astra_api-0.1.3.dist-info/METADATA
parendum_astra_api-0.1.3.dist-info/WHEEL
parendum_astra_api-0.1.3.dist-info/top_level.txt
parendum_astra_api-0.1.3.dist-info/RECORD
