Metadata-Version: 2.1
Name: parendum-astra-api
Version: 0.1.3
Summary: A library to interact with the Astra Portal API of Parendum.
Home-page: https://gitlab.com/parendumteam/parendum-astra-api
Author: Parendum OÜ
Author-email: info@parendum.com
Classifier: Programming Language :: Python :: 3
Classifier: License :: OSI Approved :: MIT License
Classifier: Operating System :: OS Independent
License-File: LICENSE
Requires-Dist: pycryptodome
Requires-Dist: requests
